fastapi_gssapi/__init__.py
fastapi_gssapi/dependency.py
fastapi_gssapi/middleware.py
fastapi_gssapi-0.1.1.dist-info/METADATA
fastapi_gssapi-0.1.1.dist-info/WHEEL
fastapi_gssapi-0.1.1.dist-info/licenses/LICENSE
fastapi_gssapi-0.1.1.dist-info/RECORD
